spade_fiware_artifacts/__init__.py
spade_fiware_artifacts/context_broker_inserter.py
spade_fiware_artifacts/context_broker_suscription_manager.py
spade_fiware_artifacts-0.1.2.dist-info/AUTHORS.rst
spade_fiware_artifacts-0.1.2.dist-info/LICENSE
spade_fiware_artifacts-0.1.2.dist-info/METADATA
spade_fiware_artifacts-0.1.2.dist-info/WHEEL
spade_fiware_artifacts-0.1.2.dist-info/entry_points.txt
spade_fiware_artifacts-0.1.2.dist-info/top_level.txt
spade_fiware_artifacts-0.1.2.dist-info/RECORD
