Metadata-Version: 2.1
Name: spade-fiware-artifacts
Version: 0.1.2
Summary: A toolkit for multi-agent systems to interact with FIWARE's context management system
Home-page: https://github.com/sosanzma/SPADE-FIWARE-Artifacts
Author: Manel Soler Sanz
Author-email: manelbng@gmail.com
License: MIT License
Keywords: spade-fiware-artifacts
Classifier: Programming Language :: Python :: 3
Classifier: License :: OSI Approved :: MIT License
Classifier: Operating System :: OS Independent
Requires-Python: >=3.8
License-File: LICENSE
License-File: AUTHORS.rst
Requires-Dist: spade-artifact ==0.2.1
Requires-Dist: psycopg2-binary ==2.9.9
